gitbook/__init__.py
gitbook/py.typed
gitbook-0.1.0.dist-info/LICENSE
gitbook-0.1.0.dist-info/WHEEL
gitbook-0.1.0.dist-info/METADATA
gitbook-0.1.0.dist-info/RECORD
