Metadata-Version: 2.1
Name: gitbook
Version: 0.1.0
Summary: Python library for interacting with GitBook's API.
License: MIT
Author: CircuitSacul
Author-email: circuitsacul@gmail.com
Requires-Python: >=3.8,<4.0
Classifier: License :: OSI Approved :: MIT License
Classifier: Programming Language :: Python :: 3
Classifier: Programming Language :: Python :: 3.8
Classifier: Programming Language :: Python :: 3.9
Classifier: Programming Language :: Python :: 3.10
